LICENSE
README.md
setup.cfg
setup.py
m_pytest_core/__init__.py
m_pytest_core.egg-info/PKG-INFO
m_pytest_core.egg-info/SOURCES.txt
m_pytest_core.egg-info/dependency_links.txt
m_pytest_core.egg-info/top_level.txt
m_pytest_core/core/__init__.py
m_pytest_core/core/allure_wrapper.py
m_pytest_core/core/helpers.py
m_pytest_core/core/db/__init__.py
m_pytest_core/core/db/db.py
m_pytest_core/core/utils/__init__.py
m_pytest_core/core/utils/testrail.py
m_pytest_core/files/__init__.py